sequmap/__init__.py
sequmap/main.py
sequmap-0.1.0.dist-info/LICENSE
sequmap-0.1.0.dist-info/METADATA
sequmap-0.1.0.dist-info/WHEEL
sequmap-0.1.0.dist-info/top_level.txt
sequmap-0.1.0.dist-info/RECORD
