Metadata-Version: 2.1
Name: sequmap
Version: 0.1.0
Summary: An AA/NT sequence encoder using umap & pca
Home-page: https://github.com/MurrellGroup/SeqUMAP
Author: Ben Murrell
Author-email: murrellb@gmail.com
License: UNKNOWN
Platform: UNKNOWN
Classifier: Programming Language :: Python :: 3
Classifier: License :: OSI Approved :: MIT License
Classifier: Operating System :: OS Independent
Requires-Python: >=3.6
License-File: LICENSE
Requires-Dist: numpy
Requires-Dist: umap-learn
Requires-Dist: scikit-learn
Requires-Dist: numba
Requires-Dist: scipy
